hot_magnet.py
handler/__init__.py
handler/magnet_handler.py
hot_magnet-0.0.1.dist-info/LICENSE
hot_magnet-0.0.1.dist-info/METADATA
hot_magnet-0.0.1.dist-info/WHEEL
hot_magnet-0.0.1.dist-info/entry_points.txt
hot_magnet-0.0.1.dist-info/top_level.txt
hot_magnet-0.0.1.dist-info/RECORD
