Metadata-Version: 2.1
Name: hot-magnet
Version: 0.0.1
Summary: Get Hot Magnet Top 20
Home-page: https://github.com/landybird/hot-magnet
Author: landybird
Author-email: 1442172978@qq.com
License: MIT
Platform: UNKNOWN
Classifier: Programming Language :: Python :: 3
Classifier: License :: OSI Approved :: MIT License
Requires-Dist: setuptools
Requires-Dist: requests
Requires-Dist: fake-useragent
Requires-Dist: requests-html
Requires-Dist: PyYAML
